LICENSE.txt
MANIFEST.in
README.rst
setup.py
bw2webreports/__init__.py
bw2webreports/app.py
bw2webreports.egg-info/PKG-INFO
bw2webreports.egg-info/SOURCES.txt
bw2webreports.egg-info/dependency_links.txt
bw2webreports.egg-info/requires.txt
bw2webreports.egg-info/top_level.txt
bw2webreports/bin/bw2-report-server.py
bw2webreports/static/blueprint/ie.css
bw2webreports/static/blueprint/print.css
bw2webreports/static/blueprint/screen.css
bw2webreports/static/blueprint/plugins/buttons/screen.css
bw2webreports/static/blueprint/plugins/buttons/icons/cross.png
bw2webreports/static/blueprint/plugins/buttons/icons/key.png
bw2webreports/static/blueprint/plugins/buttons/icons/tick.png
bw2webreports/static/blueprint/plugins/fancy-type/screen.css
bw2webreports/static/blueprint/plugins/link-icons/screen.css
bw2webreports/static/blueprint/plugins/link-icons/icons/doc.png
bw2webreports/static/blueprint/plugins/link-icons/icons/email.png
bw2webreports/static/blueprint/plugins/link-icons/icons/external.png
bw2webreports/static/blueprint/plugins/link-icons/icons/feed.png
bw2webreports/static/blueprint/plugins/link-icons/icons/im.png
bw2webreports/static/blueprint/plugins/link-icons/icons/lock.png
bw2webreports/static/blueprint/plugins/link-icons/icons/pdf.png
bw2webreports/static/blueprint/plugins/link-icons/icons/visited.png
bw2webreports/static/blueprint/plugins/link-icons/icons/xls.png
bw2webreports/static/blueprint/plugins/rtl/screen.css
bw2webreports/static/blueprint/src/forms.css
bw2webreports/static/blueprint/src/grid.css
bw2webreports/static/blueprint/src/grid.png
bw2webreports/static/blueprint/src/ie.css
bw2webreports/static/blueprint/src/print.css
bw2webreports/static/blueprint/src/reset.css
bw2webreports/static/blueprint/src/typography.css
bw2webreports/static/css/base.css
bw2webreports/static/css/index.css
bw2webreports/static/img/favicon.ico
bw2webreports/static/img/linedpaper.png
bw2webreports/static/img/llama.jpg
bw2webreports/static/img/monster.jpg
bw2webreports/static/js/force-directed.js
bw2webreports/static/js/hinton.js
bw2webreports/static/js/stepped-histogram.js
bw2webreports/templates/base.html
bw2webreports/templates/report.html