Metadata-Version: 1.1
Name: bw2webreports
Version: 0.4
Summary: UNKNOWN
Home-page: https://bitbucket.org/cmutel/brightway2-web-reports
Author: Chris Mutel
Author-email: cmutel@gmail.com
License: Copyright (c) 2013, Chris Mutel and ETH Zürich
